rezq
