Metadata-Version: 2.1
Name: rezq
Version: 0.1.1
Summary: Ensuring data quality in Delta Lake
Author-email: Marco Rezende <marcomrezende@gmail.com>
License:                                  Apache License
Project-URL: Home, https://github.com/marcorezende/rezq
Keywords: delta lake,data quality
Requires-Python: >=3.8
License-File: LICENSE
Requires-Dist: pyspark>=3.3.0
Requires-Dist: delta-spark>=2.3.0
